py-statistics/__init__.py
py-statistics/statistics.py
py_statistics/__init__.py
py_statistics/statistics.py
python_statistics-0.0.4.dist-info/METADATA
python_statistics-0.0.4.dist-info/WHEEL
python_statistics-0.0.4.dist-info/top_level.txt
python_statistics-0.0.4.dist-info/RECORD
