Metadata-Version: 2.1
Name: python-statistics
Version: 0.0.4
Summary: Module name confusion fixed
Author: Meteey (Mustafa Konur)
Author-email: <konurmustafa17@gmail.com>
Keywords: statistics,z-score,normalization
